{"version":1,"resource":"file:///home/sahith/sahith/webDevelopment/cloneAndProjects/projects/mernApplications/noteZipperMern/frontend/src/components/screens/RegisterScreen/RegisterScreen.js","entries":[{"id":"y7bF.js","timestamp":1689483090816},{"id":"XTcf.js","timestamp":1689483185142},{"id":"fQI8.js","timestamp":1689483202971},{"id":"UNgL.js","timestamp":1689483463676},{"id":"ZNSw.js","timestamp":1689483482664},{"id":"JJw9.js","timestamp":1689483504753},{"id":"miCd.js","timestamp":1689483521933},{"id":"CcsU.js","timestamp":1689483588254},{"id":"yKIx.js","timestamp":1689483649140},{"id":"TArB.js","timestamp":1689483725101},{"id":"wmnH.js","timestamp":1689483911690},{"id":"Ioiu.js","timestamp":1689483952047},{"id":"uDDC.js","timestamp":1689484044436},{"id":"6YFT.js","timestamp":1689484061913},{"id":"pAB2.js","timestamp":1689484151469},{"id":"uZQo.js","timestamp":1689506060442},{"id":"fDHY.js","timestamp":1689506154307},{"id":"qflZ.js","timestamp":1689506203925},{"id":"g84g.js","timestamp":1689506274032},{"id":"VYQw.js","timestamp":1689506368906},{"id":"1nLk.js","timestamp":1689506417755},{"id":"vUkv.js","timestamp":1689506438804},{"id":"7v7V.js","timestamp":1689506483524},{"id":"7Rja.js","timestamp":1689506496373},{"id":"NwwY.js","timestamp":1689506595450},{"id":"r42B.js","timestamp":1689508390935},{"id":"DVrc.js","timestamp":1689508417552},{"id":"h9D7.js","timestamp":1689508432840},{"id":"QzEx.js","timestamp":1689508443864},{"id":"9ckF.js","timestamp":1689508499324},{"id":"fECZ.js","timestamp":1689508622930},{"id":"aZ0k.js","timestamp":1689508649802},{"id":"nCsN.js","timestamp":1689508669634},{"id":"wJmx.js","timestamp":1689508692262},{"id":"bPFW.js","timestamp":1689508722638},{"id":"b2dY.js","timestamp":1689508752363},{"id":"ruf6.js","timestamp":1689508772803},{"id":"xJVm.js","timestamp":1689509020801},{"id":"HaGP.js","timestamp":1689509068405},{"id":"hued.js","timestamp":1689509091053},{"id":"750X.js","timestamp":1689509108218},{"id":"xAp9.js","timestamp":1689509127926},{"id":"ExSW.js","timestamp":1689509231038},{"id":"cM9m.js","timestamp":1689509242071},{"id":"8TIu.js","timestamp":1689509306841},{"id":"wJvy.js","timestamp":1689509341147},{"id":"6vfS.js","timestamp":1689509398793},{"id":"YypN.js","timestamp":1689509417813},{"id":"EApl.js","timestamp":1689865229482},{"id":"ZEBT.js","timestamp":1689865281959}]}