{"version":1,"resource":"file:///home/sahith/confidential/webDevelopment/frontEnd/react/react-by-thapa/axios/src/components/About.jsx","entries":[{"id":"GcTt.jsx","timestamp":1685282182438},{"id":"W0TP.jsx","timestamp":1685337315270},{"id":"vJ8V.jsx","timestamp":1685339909474},{"id":"eDbi.jsx","timestamp":1685339933362},{"id":"13sT.jsx","timestamp":1685339994586},{"id":"v6HB.jsx","timestamp":1685340017178},{"id":"4YIn.jsx","timestamp":1685340032134},{"id":"RcWH.jsx","timestamp":1685340112362},{"id":"LZTf.jsx","timestamp":1685340243943},{"id":"HKdO.jsx","timestamp":1685340408757},{"id":"IKF9.jsx","timestamp":1685340459405},{"id":"fRMZ.jsx","timestamp":1685340494478},{"id":"Nc9d.jsx","timestamp":1685340516614},{"id":"9Psq.jsx","timestamp":1685364509243},{"id":"19Zf.jsx","timestamp":1685364585056},{"id":"GoUA.jsx","timestamp":1685364602032},{"id":"N772.jsx","timestamp":1685364660233},{"id":"Txju.jsx","timestamp":1685364678626},{"id":"IByQ.jsx","timestamp":1685364815151},{"id":"ioks.jsx","timestamp":1685364849924},{"id":"eL1l.jsx","timestamp":1685364860948},{"id":"jC2X.jsx","timestamp":1685364896388},{"id":"lom3.jsx","timestamp":1685365197312},{"id":"W1z5.jsx","timestamp":1685422366125},{"id":"gUdU.jsx","timestamp":1685422514473}]}