{"version":1,"resource":"file:///home/sahith/confidential/react-by-thapa/learnring/src/App.js","entries":[{"id":"VtSj.js","timestamp":1679807619412},{"id":"D4B9.js","timestamp":1679807636111},{"id":"1n3m.js","timestamp":1679807662770},{"id":"4Hnm.js","timestamp":1679807691777},{"id":"lFx2.js","timestamp":1679807760600},{"id":"31KR.js","timestamp":1679807773321},{"id":"7Teh.js","timestamp":1679807790102},{"id":"Iizy.js","timestamp":1679807803266},{"id":"4Wug.js","timestamp":1679807834949},{"id":"Zkx8.js","timestamp":1679807915065},{"id":"1kEp.js","timestamp":1679807966744},{"id":"iPHZ.js","timestamp":1679808007311},{"id":"GZth.js","timestamp":1679808025088},{"id":"fxLm.js","timestamp":1679808093016},{"id":"rHih.js","timestamp":1679808124607},{"id":"Km3s.js","timestamp":1679808139447},{"id":"UntA.js","timestamp":1679808166820},{"id":"y7gL.js","timestamp":1679808253270},{"id":"5KwY.js","timestamp":1679808327170},{"id":"bXUc.js","timestamp":1679808415346},{"id":"NeA1.js","timestamp":1679808437668},{"id":"SCoJ.js","timestamp":1679808467941},{"id":"b2AQ.js","timestamp":1679808693063},{"id":"ph4m.js","timestamp":1679808720076},{"id":"kO2Q.js","timestamp":1679808771361},{"id":"H2uq.js","timestamp":1679808790654},{"id":"HjG1.js","timestamp":1679808809694},{"id":"NyPz.js","timestamp":1679808836555},{"id":"3lg6.js","timestamp":1679808857852},{"id":"2JZm.js","timestamp":1679808886449},{"id":"EOXN.js","source":"undoRedo.source","timestamp":1679808887633},{"id":"vZSc.js","timestamp":1679808895697},{"id":"NqF5.js","timestamp":1679808906962},{"id":"l6bR.js","timestamp":1679808939119},{"id":"zKmc.js","timestamp":1679808990629},{"id":"RRBh.js","timestamp":1679809018490},{"id":"tuWv.js","timestamp":1679809031739},{"id":"0oWN.js","timestamp":1679809150321},{"id":"plTn.js","timestamp":1679809216576},{"id":"kaod.js","timestamp":1679810250016},{"id":"xKqk.js","timestamp":1679810286305},{"id":"fIbC.js","source":"Workspace Edit","timestamp":1679810287865},{"id":"mDTv.js","timestamp":1679810289865},{"id":"6lfm.js","timestamp":1679810902137},{"id":"6oWo.js","timestamp":1679811041471},{"id":"2Zb9.js","source":"Workspace Edit","timestamp":1679811043495},{"id":"9mLE.js","timestamp":1679811045075},{"id":"t8Xi.js","timestamp":1682327710989},{"id":"1YGW.js","source":"undoRedo.source","timestamp":1682327712361},{"id":"oQG8.js","source":"moved.source","timestamp":1682327868462}]}