{"version":1,"resource":"file:///home/sahith/confidential/react/react-by-thapa/netflix/src/App.js","entries":[{"id":"wqjS.js","timestamp":1682420621922},{"id":"BoPD.js","timestamp":1682420650174},{"id":"Bk5I.js","timestamp":1682420667751},{"id":"3Ppy.js","timestamp":1682420688239},{"id":"xvXm.js","timestamp":1682420799241},{"id":"qRm3.js","timestamp":1682420810325},{"id":"dJNz.js","timestamp":1682420846030},{"id":"GSgi.js","source":"undoRedo.source","timestamp":1682420847558},{"id":"cTt9.js","timestamp":1682420883930},{"id":"pfA8.js","timestamp":1682420903103},{"id":"ACDP.js","timestamp":1682420970776},{"id":"DCB2.js","source":"undoRedo.source","timestamp":1682420979268},{"id":"hnUo.js","timestamp":1682421207212},{"id":"8jLw.js","timestamp":1682596374096},{"id":"Kg8n.js","timestamp":1682596398369},{"id":"nbPc.js","timestamp":1682596419505},{"id":"ehDF.js","timestamp":1682596563391}]}