{"version":1,"resource":"file:///home/sahith/confidential/whatAppCloneSecondTime/js/client.js","entries":[{"id":"jPBo.js","timestamp":1681913704676},{"id":"hwDC.js","timestamp":1681913756664},{"id":"Iwg1.js","timestamp":1681913931002},{"id":"7nLM.js","timestamp":1681913963317},{"id":"QfEa.js","timestamp":1681914001084},{"id":"vFiL.js","timestamp":1681914066357},{"id":"8kNT.js","timestamp":1681914092881},{"id":"zWxv.js","source":"undoRedo.source","timestamp":1681914096833},{"id":"3Yls.js","timestamp":1681914165878},{"id":"1RaL.js","timestamp":1681914205798},{"id":"6ACB.js","timestamp":1681914295578}]}