{"version":1,"resource":"file:///home/sahith/sahith/webDevelopment/cloneAndProjects/projects/mernApplications/advancedAuth/backend/routes/userRoutes.js","entries":[{"id":"sk1w.js","timestamp":1699533976442},{"id":"5Blb.js","timestamp":1699534010123},{"id":"Dw2Q.js","timestamp":1699542870691},{"id":"tQPS.js","timestamp":1699543333667},{"id":"qy3c.js","timestamp":1699543378840},{"id":"kfLC.js","timestamp":1699543863917},{"id":"ZAhp.js","timestamp":1699714670036},{"id":"vkQD.js","timestamp":1699714931484},{"id":"W9gz.js","timestamp":1699714943240},{"id":"9ytd.js","timestamp":1699715010213},{"id":"jpeR.js","timestamp":1699715042249},{"id":"oRQ6.js","timestamp":1699715436292},{"id":"ksSj.js","timestamp":1699717007886},{"id":"MczL.js","source":"Workspace Edit","timestamp":1699717010082},{"id":"Lrxy.js","timestamp":1699717610346},{"id":"luh2.js","timestamp":1699717629830},{"id":"fUtn.js","source":"Workspace Edit","timestamp":1699717631042},{"id":"q3oJ.js","timestamp":1699870573696},{"id":"b6Tx.js","timestamp":1699870626364}]}