{"version":1,"resource":"file:///home/sahith/confidential/webDevelopment/cloneAndProjects/projects/nodeProjects/socketProjects/chatCodersGyan/public/client.js","entries":[{"id":"BvI7.js","timestamp":1684048744813},{"id":"MPwD.js","source":"undoRedo.source","timestamp":1684048746785},{"id":"mpnX.js","timestamp":1684048747913},{"id":"c9Pe.js","timestamp":1684048796158},{"id":"C0aE.js","timestamp":1684048858588},{"id":"xaiN.js","timestamp":1684048873472},{"id":"OuQy.js","timestamp":1684048916637},{"id":"MrTN.js","timestamp":1684049123362},{"id":"eZwz.js","timestamp":1684057459859},{"id":"gzVy.js","timestamp":1684057523101},{"id":"UdmO.js","timestamp":1684057568989},{"id":"C4jj.js","timestamp":1684057584294},{"id":"IWbW.js","timestamp":1684058118244},{"id":"wY4P.js","source":"undoRedo.source","timestamp":1684058121532},{"id":"jqgu.js","timestamp":1684058138132},{"id":"OJgM.js","timestamp":1684058154264},{"id":"zNxi.js","timestamp":1684058196277},{"id":"hRBI.js","timestamp":1684058232026},{"id":"VRXD.js","timestamp":1684058272394},{"id":"enmz.js","timestamp":1684058302563},{"id":"CflQ.js","timestamp":1684058409561},{"id":"RwxQ.js","timestamp":1684058465425},{"id":"qmKq.js","timestamp":1684058476454},{"id":"d0Em.js","timestamp":1684058488390},{"id":"EM7u.js","timestamp":1684058541382},{"id":"MHj4.js","timestamp":1684058566631},{"id":"SkKo.js","timestamp":1684058600711},{"id":"KjNp.js","timestamp":1684058713561},{"id":"yNkL.js","timestamp":1684058797890},{"id":"HoGj.js","timestamp":1684058824270},{"id":"nKFI.js","timestamp":1684058872174},{"id":"dfee.js","timestamp":1684058971901},{"id":"mSrv.js","timestamp":1684059323653},{"id":"1dpi.js","timestamp":1684059348101},{"id":"O1MY.js","timestamp":1684059363425},{"id":"sMsL.js","timestamp":1684059409774},{"id":"AGGa.js","timestamp":1684059447459},{"id":"PqjO.js","timestamp":1684059666747},{"id":"k6dW.js","timestamp":1684059753292},{"id":"h1Cq.js","timestamp":1684059855434},{"id":"E6ng.js","timestamp":1684059925719},{"id":"xTiN.js","timestamp":1684060497247},{"id":"GY1F.js","timestamp":1684061278990},{"id":"ttLI.js","timestamp":1684061295354}]}