{"version":1,"resource":"file:///home/sahith/confidential/cloneAndProjects/projects/mongoDbWebsite/src/app.js","entries":[{"id":"DTIK.js","timestamp":1682856992716},{"id":"kFQJ.js","timestamp":1682857008989},{"id":"b7yz.js","timestamp":1682857124328},{"id":"JKxO.js","timestamp":1682857346086},{"id":"oNoi.js","source":"undoRedo.source","timestamp":1682857347458},{"id":"aQ4v.js","timestamp":1682857352907},{"id":"bwDn.js","timestamp":1682857393820},{"id":"xi0A.js","timestamp":1682857433008},{"id":"D9Pt.js","source":"undoRedo.source","timestamp":1682857460381},{"id":"rCxT.js","timestamp":1682857471737},{"id":"8fpZ.js","timestamp":1682857548031},{"id":"m7DF.js","timestamp":1682857866793},{"id":"f3OS.js","timestamp":1682858060268},{"id":"C7YP.js","timestamp":1682858127649},{"id":"5IHL.js","timestamp":1682859147581},{"id":"ttUy.js","timestamp":1682859216983},{"id":"osPe.js","timestamp":1682859254104},{"id":"N1fT.js","timestamp":1682859279781},{"id":"KHYR.js","timestamp":1682859305114},{"id":"Tmt3.js","timestamp":1682859349295},{"id":"xfPQ.js","timestamp":1682859367336},{"id":"swBM.js","timestamp":1682859380420},{"id":"mFoB.js","source":"undoRedo.source","timestamp":1682859381536},{"id":"LJ8R.js","timestamp":1682859387824},{"id":"fpgY.js","timestamp":1682859398808},{"id":"ondM.js","timestamp":1682859427037},{"id":"RN4u.js","timestamp":1682859553956},{"id":"rPPb.js","timestamp":1682859831995},{"id":"vxNK.js","timestamp":1682859849271},{"id":"V5o6.js","timestamp":1682859982486},{"id":"jW7Z.js","timestamp":1683098855378},{"id":"mi3d.js","source":"undoRedo.source","timestamp":1683098867386},{"id":"xPJU.js","timestamp":1683098876714},{"id":"lBCk.js","source":"undoRedo.source","timestamp":1683098897662},{"id":"b35i.js","timestamp":1683098899690},{"id":"UhZA.js","timestamp":1683098922191},{"id":"69rh.js","timestamp":1683098946379},{"id":"HxoE.js","source":"undoRedo.source","timestamp":1683098954091},{"id":"v6a4.js","timestamp":1683098967955},{"id":"V4M1.js","timestamp":1683099062461},{"id":"xW7t.js","timestamp":1683099601518},{"id":"qDnm.js","source":"undoRedo.source","timestamp":1683099605046},{"id":"87Jz.js","timestamp":1683099619999},{"id":"SueM.js","source":"undoRedo.source","timestamp":1683099626687},{"id":"bTIP.js","timestamp":1683099638907},{"id":"D5Fd.js","timestamp":1683099657479}]}