{"version":1,"resource":"file:///home/sahith/confidential/whatAppCloneSecondTime/index.html","entries":[{"id":"ElkS.html","timestamp":1681910187327},{"id":"uTgw.html","timestamp":1681910241876},{"id":"6rkY.html","source":"undoRedo.source","timestamp":1681910247572},{"id":"Kuix.html","timestamp":1681910267433},{"id":"558s.html","timestamp":1681910281473},{"id":"3lMn.html","timestamp":1681910303769},{"id":"7KG6.html","timestamp":1681910383107},{"id":"ESJZ.html","timestamp":1681910393267},{"id":"aVsS.html","timestamp":1681910794164},{"id":"PLoL.html","timestamp":1681910901575},{"id":"Ghfs.html","timestamp":1681913788226},{"id":"GZin.html","timestamp":1681913816318},{"id":"RbC6.html","source":"undoRedo.source","timestamp":1681914128051}]}