{"version":1,"resource":"file:///home/sahith/confidential/cloneApplicatoins/spotifyClone/style.css","entries":[{"id":"h5QT.css","timestamp":1679387844527},{"id":"r724.css","timestamp":1679387863748},{"id":"hBEJ.css","source":"undoRedo.source","timestamp":1679387868296},{"id":"om7i.css","timestamp":1679387877188},{"id":"SSiF.css","timestamp":1679387898984},{"id":"iDCE.css","timestamp":1679387915025},{"id":"w5wh.css","timestamp":1679387927057},{"id":"gEcj.css","timestamp":1679387948401},{"id":"4nTG.css","timestamp":1679388100028},{"id":"BiUM.css","timestamp":1679388123537},{"id":"vqX7.css","timestamp":1679388362926},{"id":"hYbO.css","timestamp":1679388392706},{"id":"lnvB.css","timestamp":1679388429391},{"id":"auTS.css","timestamp":1679388476872}]}